neurolabszia/__init__.py
neurolabszia/cli.py
neurolabszia/client.py
neurolabszia/config.py
neurolabszia/endpoints/__init__.py
neurolabszia/endpoints/base.py
neurolabszia/endpoints/catalog.py
neurolabszia/endpoints/image_recognition.py
neurolabszia/examples/IR Results Neurolabs Ingestion [DB Integration].ipynb
neurolabszia/examples/basic_usage.py
neurolabszia/examples/end_to_end_workflow.py
neurolabszia/examples/example_raw_json_usage.py
neurolabszia/exceptions.py
neurolabszia/http/__init__.py
neurolabszia/http/session.py
neurolabszia/models/__init__.py
neurolabszia/models/catalog.py
neurolabszia/models/image_recognition.py
neurolabszia/tests/.env.test
neurolabszia/tests/conftest.py
neurolabszia/tests/test_catalog.py
neurolabszia/tests/test_client.py
neurolabszia/tests/test_dataframe.py
neurolabszia/tests/test_integration.py
neurolabszia/tests/test_ir_category_fields.py
neurolabszia/utils/__init__.py
neurolabszia/utils/dataframe.py
zia_sdk_python-0.0.20.dist-info/METADATA
zia_sdk_python-0.0.20.dist-info/WHEEL
zia_sdk_python-0.0.20.dist-info/entry_points.txt
zia_sdk_python-0.0.20.dist-info/RECORD
