Metadata-Version: 2.3
Name: zia-sdk-python
Version: 0.0.20
Summary: Python SDK for Neurolabs ZIA platform
License: MIT
Author: Neurolabs
Author-email: support@neurolabs.ai
Maintainer: Patric Fulop
Maintainer-email: patric@neurolabs.ai
Requires-Python: >=3.11
Classifier: Development Status :: 3 - Alpha
Classifier: Intended Audience :: Developers
Classifier: License :: OSI Approved :: MIT License
Classifier: Operating System :: OS Independent
Classifier: Programming Language :: Python :: 3.11
Classifier: Programming Language :: Python :: 3.12
Classifier: Programming Language :: Python :: 3.13
Classifier: Topic :: Scientific/Engineering :: Artificial Intelligence
Classifier: Topic :: Software Development :: Libraries :: Python Modules
Provides-Extra: databricks
Provides-Extra: pandas
Requires-Dist: httpx (>=0.28.1,<0.29.0)
Requires-Dist: pandas (>=2.2.3,<3.0.0) ; extra == "databricks"
Requires-Dist: pandas (>=2.2.3,<3.0.0) ; extra == "pandas"
Requires-Dist: pydantic (>=2.11.7,<3.0.0)
Requires-Dist: pyspark (>=3.4.0,<4.0.0) ; extra == "databricks"
Requires-Dist: pytest (>=8.4.1,<9.0.0)
Requires-Dist: pytest-asyncio (>=1.1.0,<2.0.0)
Requires-Dist: pytest-cov (>=6.2.1,<7.0.0)
Requires-Dist: python-dotenv (>=1.1.1,<2.0.0)
